mcDETECT/__init__.py
mcDETECT/model.py
mcDETECT/utils.py
mcdetect-2.0.12.dist-info/licenses/LICENSE
mcdetect-2.0.12.dist-info/METADATA
mcdetect-2.0.12.dist-info/WHEEL
mcdetect-2.0.12.dist-info/top_level.txt
mcdetect-2.0.12.dist-info/RECORD
