Metadata-Version: 2.4
Name: mcDETECT
Version: 2.0.12
Summary: Uncovering the dark transcriptome in polarized neuronal compartments with mcDETECT
Home-page: https://github.com/chen-yang-yuan/mcDETECT
Author: Chenyang Yuan
Author-email: chenyang.yuan@emory.edu
Classifier: Programming Language :: Python :: 3
Classifier: License :: OSI Approved :: MIT License
Classifier: Operating System :: OS Independent
Requires-Python: >=3.6
License-File: LICENSE
Requires-Dist: anndata
Requires-Dist: miniball
Requires-Dist: numpy
Requires-Dist: pandas
Requires-Dist: rtree
Requires-Dist: scanpy
Requires-Dist: scikit-learn
Requires-Dist: scipy
Requires-Dist: shapely
Dynamic: author
Dynamic: author-email
Dynamic: classifier
Dynamic: description
Dynamic: description-content-type
Dynamic: home-page
Dynamic: license-file
Dynamic: requires-dist
Dynamic: requires-python
Dynamic: summary
